Metadata-Version: 1.0
Name: aksh-distributions
Version: 1.5
Summary: Gaussian distributions
Home-page: UNKNOWN
Author: Abdalkarim Shehab
Author-email: abdo.r.shehab2@gmail.com
License: UNKNOWN
Platform: UNKNOWN
